pomice/__init__.py
pomice/enums.py
pomice/events.py
pomice/exceptions.py
pomice/filters.py
pomice/objects.py
pomice/player.py
pomice/pool.py
pomice/utils.py
pomice/spotify/__init__.py
pomice/spotify/album.py
pomice/spotify/client.py
pomice/spotify/exceptions.py
pomice/spotify/playlist.py
pomice/spotify/track.py
disnake_pomice-2.0.0.dist-info/LICENSE
disnake_pomice-2.0.0.dist-info/METADATA
disnake_pomice-2.0.0.dist-info/WHEEL
disnake_pomice-2.0.0.dist-info/top_level.txt
disnake_pomice-2.0.0.dist-info/RECORD
